CHANGES.txt
README.txt
bootstrap.py
buildout.cfg
setup.py
src/manuelpi/__init__.py
src/manuelpi.fakemodule.egg-info/PKG-INFO
src/manuelpi.fakemodule.egg-info/SOURCES.txt
src/manuelpi.fakemodule.egg-info/dependency_links.txt
src/manuelpi.fakemodule.egg-info/namespace_packages.txt
src/manuelpi.fakemodule.egg-info/not-zip-safe
src/manuelpi.fakemodule.egg-info/requires.txt
src/manuelpi.fakemodule.egg-info/top_level.txt
src/manuelpi/fakemodule/README.txt
src/manuelpi/fakemodule/__init__.py
src/manuelpi/fakemodule/fakemodule.py
src/manuelpi/fakemodule/fakemodule.txt
src/manuelpi/fakemodule/tests.py