Metadata-Version: 1.0
Name: manuelpi.fakemodule
Version: 0.1a
Summary: Module support in doctests
Home-page: http://www.python.org/pypi/manuelpi.fakemodule
Author: Paul Wilson
Author-email: paulalexwilson@gmail.com
License: ZPL 2.1
Platform: UNKNOWN
Classifier: Intended Audience :: Developers
Classifier: License :: OSI Approved :: Zope Public License
Classifier: Programming Language :: Python
